{
  "config": {
    "abort": {
      "single_instance_allowed": "Only one camera entry is allowed."
    },
    "step": {
      "user": {
        "title": "Termux camera",
        "description": "Configure camera capture settings.",
        "data": {
          "name": "Name",
          "camera_id": "Camera ID",
          "www_subdir": "WWW subdirectory",
          "keep_latest": "How many latest photos to keep in the gallery list"
        }
      }
    }
  },
  "options": {
    "step": {
      "init": {
        "title": "Camera options",
        "data": {
          "camera_id": "Camera ID",
          "www_subdir": "WWW subdirectory",
          "keep_latest": "How many latest photos to keep in the gallery list"
        }
      }
    }
  }
}